Gemi3/Model1.py
Gemi3/Score.py
Gemi3/__init__.py
Gemi3/g3datahandling.py
Gemi3/rsCAVI.pypy38-pp73-darwin.so
Gemi3/pyCAVI/__init__.py
Gemi3/pyCAVI/_update_MAE.py
Gemi3/pyCAVI/_update_r.py
Gemi3/pyCAVI/_update_s.py
Gemi3/pyCAVI/_update_tau.py
Gemi3/pyCAVI/_update_x.py
Gemi3/pyCAVI/_update_y.py
Gemi3/pyCAVI/util.py
Gemi3-1.0.dist-info/LICENSE.md
Gemi3-1.0.dist-info/METADATA
Gemi3-1.0.dist-info/WHEEL
Gemi3-1.0.dist-info/top_level.txt
Gemi3-1.0.dist-info/RECORD
