Metadata-Version: 2.1
Name: Gemi3
Version: 1.0
Classifier: Programming Language :: Python
Classifier: Programming Language :: Rust
Requires-Python: >=3.8
License-File: LICENSE.md
Requires-Dist: numpy
Requires-Dist: pandas
Requires-Dist: scikit-learn
Requires-Dist: statsmodels
